modeltranslation_lokalise/__init__.py
modeltranslation_lokalise/apps.py
modeltranslation_lokalise/lokalise_client.py
modeltranslation_lokalise/models.py
modeltranslation_lokalise/permissions.py
modeltranslation_lokalise/serializers.py
modeltranslation_lokalise/signals.py
modeltranslation_lokalise/views.py
modeltranslation_lokalise/migrations/__init__.py
modeltranslation_lokalise-0.1.8.dist-info/LICENSE
modeltranslation_lokalise-0.1.8.dist-info/METADATA
modeltranslation_lokalise-0.1.8.dist-info/WHEEL
modeltranslation_lokalise-0.1.8.dist-info/top_level.txt
modeltranslation_lokalise-0.1.8.dist-info/RECORD
