Metadata-Version: 2.1
Name: modeltranslation-lokalise
Version: 0.1.8
Summary: Integrate django-modeltranslation with lokalise.co
Home-page: https://github.com/chisvi/modeltranslation-lokalise
Author: Sergi Chisvert
Author-email: chisvi@gmail.com
License: MIT
Download-URL: https://github.com/chisvi/modeltranslation-lokalise/archive/0.1.8.tar.gz
Keywords: Django,django-modeltranslation,translation,lokalise
Platform: UNKNOWN
Classifier: License :: OSI Approved :: MIT License
Classifier: Intended Audience :: Developers
Classifier: Programming Language :: Python :: 3
Classifier: Programming Language :: Python :: 3.6
Classifier: Development Status :: 3 - Alpha
Requires-Dist: django
Requires-Dist: django-modeltranslation
Requires-Dist: djangorestframework
Requires-Dist: requests
Requires-Dist: django-ipware
